spectral_metric/__init__.py
spectral_metric/estimator.py
spectral_metric/lib.py
spectral_metric/types.py
spectral_metric/visualize.py
spectral_metric-0.6.1.dist-info/LICENSE
spectral_metric-0.6.1.dist-info/WHEEL
spectral_metric-0.6.1.dist-info/METADATA
spectral_metric-0.6.1.dist-info/RECORD
