Metadata-Version: 2.1
Name: spectral-metric
Version: 0.6.1
Summary: Implementation of Cumulative Spectral Gradient (CSG), a measure to estimate the complexity of datasets. This works has been presented at CVPR 2019.
License: MIT
Author: Dref360
Author-email: frederic.branchaud.charron@gmail.com
Requires-Python: >=3.8,<4.0
Classifier: License :: OSI Approved :: MIT License
Classifier: Programming Language :: Python :: 3
Classifier: Programming Language :: Python :: 3.10
Classifier: Programming Language :: Python :: 3.8
Classifier: Programming Language :: Python :: 3.9
Requires-Dist: joblib (>=1.1.0,<2.0.0)
Requires-Dist: matplotlib (>=3.5.0,<4.0.0)
Requires-Dist: scikit-learn (>=1.0.1,<2.0.0)
Requires-Dist: seaborn (>=0.11.2,<0.12.0)
